XueKit/__init__.py
XueKit/get_ascending_optimizer_params.py
XueKit-0.0.4.dist-info/METADATA
XueKit-0.0.4.dist-info/WHEEL
XueKit-0.0.4.dist-info/top_level.txt
XueKit-0.0.4.dist-info/RECORD
